clustergrammer2/__init__.py
clustergrammer2/_frontend.py
clustergrammer2/_version.py
clustergrammer2/example.py
clustergrammer2/clustergrammer_fun/__init__.py
clustergrammer2/clustergrammer_fun/calc_clust.py
clustergrammer2/clustergrammer_fun/cat_pval.py
clustergrammer2/clustergrammer_fun/categories.py
clustergrammer2/clustergrammer_fun/data_formats.py
clustergrammer2/clustergrammer_fun/downsample_fun.py
clustergrammer2/clustergrammer_fun/enrichr_functions.py
clustergrammer2/clustergrammer_fun/export_data.py
clustergrammer2/clustergrammer_fun/iframe_web_app.py
clustergrammer2/clustergrammer_fun/initialize_net.py
clustergrammer2/clustergrammer_fun/load_data.py
clustergrammer2/clustergrammer_fun/load_vect_post.py
clustergrammer2/clustergrammer_fun/make_clust_fun.py
clustergrammer2/clustergrammer_fun/make_sim_mat.py
clustergrammer2/clustergrammer_fun/make_unique_labels.py
clustergrammer2/clustergrammer_fun/make_viz.py
clustergrammer2/clustergrammer_fun/normalize_fun.py
clustergrammer2/clustergrammer_fun/proc_df_labels.py
clustergrammer2/clustergrammer_fun/run_filter.py
clustergrammer2/labextension/package.json
clustergrammer2/labextension/static/183.f6e9b866008f42f8d7e5.js
clustergrammer2/labextension/static/183.f6e9b866008f42f8d7e5.js.LICENSE.txt
clustergrammer2/labextension/static/367.bfa89c907e6aad795051.js
clustergrammer2/labextension/static/480.9946b3b867399b089e55.js
clustergrammer2/labextension/static/568.d068b6c89732aded6ccf.js
clustergrammer2/labextension/static/693.519239b92a57f4ff0032.js
clustergrammer2/labextension/static/remoteEntry.4c8a0d79754fcf4e4a1d.js
clustergrammer2/labextension/static/style.js
clustergrammer2/nbextension/extension.js
clustergrammer2/nbextension/index.js
clustergrammer2/nbextension/index.js.LICENSE.txt
clustergrammer2/nbextension/index.js.map
clustergrammer2/tests/__init__.py
clustergrammer2/tests/conftest.py
clustergrammer2/tests/test_example.py
clustergrammer2/tests/test_nbextension_path.py
clustergrammer2-0.18.0.dist-info/LICENSE.txt
clustergrammer2-0.18.0.dist-info/METADATA
clustergrammer2-0.18.0.dist-info/WHEEL
clustergrammer2-0.18.0.dist-info/top_level.txt
clustergrammer2-0.18.0.dist-info/RECORD
